cell_content/__init__.py
cell_content/getcellcontent.py
get_cell-0.0.4.dist-info/LICENSE
get_cell-0.0.4.dist-info/METADATA
get_cell-0.0.4.dist-info/WHEEL
get_cell-0.0.4.dist-info/top_level.txt
get_cell-0.0.4.dist-info/RECORD
