Metadata-Version: 2.1
Name: get-cell
Version: 0.0.4
Summary: A package cell certain text in specific cell Jupyter Noebook
Author-email: Triet Le <trietltm.h@gmail.com>
Project-URL: Homepage, https://github.com/LeTriet17
Classifier: Programming Language :: Python :: 3
Classifier: License :: OSI Approved :: MIT License
Classifier: Operating System :: OS Independent
Requires-Python: >=3.7
License-File: LICENSE
